{
  "abilities": {
    "melee": {
      "ability": 2,
      "defense": 12,
      "noncombat": 2
    },
    "agility": {
      "ability": 1,
      "defense": 11,
      "noncombat": 1
    },
    "resilience": {
      "ability": 1,
      "defense": 11,
      "noncombat": 1
    },
    "vigilance": {
      "ability": 3,
      "defense": 13,
      "noncombat": 3
    },
    "ego": {
      "ability": 6,
      "defense": 16,
      "noncombat": 8
    },
    "logic": {
      "ability": 2,
      "defense": 16,
      "noncombat": 2
    }
  },
  "color": 3148640,
  "damage": {
    "melee": {
      "multiplier": 3,
      "ability": 2
    },
    "agility": {
      "multiplier": 3,
      "ability": 1
    },
    "ego": {
      "multiplier": 5,
      "ability": 8
    },
    "logic": {
      "multiplier": 3,
      "ability": 2
    }
  },
  "damageReduction": 0,
  "focus": 90,
  "health": 30,
  "initiative": {
    "value": 3,
    "edge": false
  },
  "karma": 3,
  "name": "Vael",
  "photoUrl": "https://r2vq.github.io/MarvelProfiles/img/vael.png",
  "powers": ["Astral Form", "Bolts of Balthakk", "Brain Drain", "Crimson Bands of Cyttorak", "Discipline 1", "Discipline 2", "Disguise", "Flames of the Faltine", "Images of Ikonn", "Leech Life", "Mists of Munnopor", "Shield of the Seraphim", "Vapors of Valtorr", "Wisdom"],
  "rank": 3,
  "secretIdentity": "Vaelaris the Wayward",
  "speed": { "Run": 5, "Climb": 3, "Swim": 3, "Flight": 15 },
  "tags": ["Black Market Access", "Heroic", "Sorcerous", "Supernatural"],
  "theme": "theme-vael",
  "traits": ["Connections", "Interrogation", "Leverage", "Magic Item Reliance", "Sneaky"]
}
